cli/__init__.py
cli/main.py
cloud_storage/aws_s3_cloud_storage_agent.py
cloud_storage/azure_blob_storage_agent.py
cloud_storage/cloud_storage_agent.py
cloud_storage/gcp_cloud_storage_agent.py
enhanced_examples_with_tutorial/__init__.py
enhanced_examples_with_tutorial/advanced_cases.py
enhanced_examples_with_tutorial/advanced_formatting.py
enhanced_examples_with_tutorial/all_formatters.py
enhanced_examples_with_tutorial/basic_usage.py
enhanced_examples_with_tutorial/convert_between_formats.py
enhanced_examples_with_tutorial/edge_cases_and_tags.py
enhanced_examples_with_tutorial/from_file_io.py
enhanced_examples_with_tutorial/load_convert_formats.py
enhanced_examples_with_tutorial/load_from_cloud.py
enhanced_examples_with_tutorial/manipulation_example.py
enhanced_examples_with_tutorial/parse_from_string.py
enhanced_examples_with_tutorial/parse_tuples_and_dataclass.py
enhanced_examples_with_tutorial/revive_with_typing.py
enhanced_examples_with_tutorial/strict_vs_relaxed_demo.py
enhanced_examples_with_tutorial/trigger_strict_from_file.py
enhanced_examples_with_tutorial/validate_each_format.py
enhanced_examples_with_tutorial/validate_input.py
formatters/atom.py
formatters/base.py
formatters/csv.py
formatters/env.py
formatters/html.py
formatters/ini.py
formatters/java_properties.py
formatters/json.py
formatters/jsonld.py
formatters/markdown.py
formatters/microdata.py
formatters/notation3.py
formatters/ntriples.py
formatters/owl.py
formatters/rdf.py
formatters/rss.py
formatters/shell_script.py
formatters/sparql.py
formatters/sql.py
formatters/strictyml.py
formatters/toml.py
formatters/turtle_ttl.py
formatters/xml.py
formatters/yaml.py
hyoml-0.0.2.dist-info/licenses/LICENSE
interface/__init__.py
interface/hyoml.py
interface/helpers/aliases.py
interface/helpers/format_helpers.py
interface/helpers/validation_helpers.py
loader/aggregator.py
loader/executor.py
loader/loader_manager.py
loader/normalizer.py
loader/strategies/azure_loader.py
loader/strategies/base_strategy.py
loader/strategies/data_url_loader.py
hyoml-0.0.2.dist-info/METADATA
hyoml-0.0.2.dist-info/WHEEL
hyoml-0.0.2.dist-info/top_level.txt
hyoml-0.0.2.dist-info/RECORD
