Metadata-Version: 2.4
Name: hyoml
Version: 0.0.2
Summary: Hyoml - Intelligent Relaxed Data Parser and Formatter
Home-page: https://github.com/progdaif/hyoml
Author: Ahmed Daif
Author-email: Ahmed Daif <prog.ahmeddaif@gmail.com>
License: MIT
Keywords: hyoml,relaxed-json,yaml,parser,formatter,data-processing
Requires-Python: >=3.8
License-File: LICENSE
Requires-Dist: beautifulsoup4>=4.12.2
Requires-Dist: rdflib>=6.3.2
Requires-Dist: requests>=2.31.0
Dynamic: author
Dynamic: home-page
Dynamic: license-file
Dynamic: requires-python
